[{"id":15768,"round":19,"date":"2020-10-01T09:40:00Z","venue":"Adelaide Oval","home":"Port Adelaide","away":"Geelong","margin":-3.049555561,"prHome":0.521603729,"prAway":0.4563099424,"prDraw":0.0216408081},{"id":15769,"round":19,"date":"2020-10-02T09:50:00Z","venue":"Gabba","home":"Brisbane","away":"Richmond","margin":-10.1201031726,"prHome":0.4434511079,"prAway":0.5345329026,"prDraw":0.0216408081},{"id":15770,"round":19,"date":"2020-10-03T06:40:00Z","venue":"Gabba","home":"St Kilda","away":"Western Bulldogs","margin":-5.1610040129,"prHome":0.4320572352,"prAway":0.546008658,"prDraw":0.0216408081},{"id":15771,"round":19,"date":"2020-10-03T10:10:00Z","venue":"Optus Stadium","home":"West Coast","away":"Collingwood","margin":1.8446476069,"prHome":0.5753960163,"prAway":0.4029631756,"prDraw":0.0216408081}]